Workbook

Sheet Client Subscriptions
A1: Client Email | B1: Product | C1: Plan | D1: Start Date | E1: Expiry Date | F1: Days Left | G1: Cost Price | H1: Selling Price | I1: Profit | J1: Payment Status | K1: Payment Date | L1: Renewal Status | M1: Account Type | N1: Payment Method | O1: Notes | T1: Plan | U1: Days
A2: arzhang.china7@outlook.com | B2: chatgpt | C2: 1 Month | D2: 46100 | E2: =IF(C2<>"",D2+VLOOKUP(C2,$T$2:$U$6,2,FALSE),"") -> 46130 | F2: =IF(E2<>"",E2-TODAY(),"") -> 23 | G2: 5 | H2: 35 | I2: =IF(H2<>"",H2-G2,"") -> 30 | J2: Paid | K2: =IF(J2<>"",TODAY(),"") -> 46107 | L2: Renewed | M2: Private | N2: WeChat | O2: 2 | T2: 1 Month | U2: 30
A3: yooolozin@gmail.com | B3: chatgpt | C3: 1 Month | D3: 46101 | E3: =IF(C3<>"",D3+VLOOKUP(C3,$T$2:$U$6,2,FALSE),"") -> 46131 | F3: =IF(E3<>"",E3-TODAY(),"") -> 24 | G3: 5 | H3: 35 | I3: =IF(H3<>"",H3-G3,"") -> 30 | J3: Pending | K3: =IF(J3<>"",TODAY(),"") -> 46107 | L3: Renewed | M3: Private | N3: WeChat | O3: 2 | T3: 2 Months | U3: 60
A4: 8216me@gmail.com | B4: chatgpt | C4: 1 Month | D4: 46101 | E4: =IF(C4<>"",D4+VLOOKUP(C4,$T$2:$U$6,2,FALSE),"") -> 46131 | F4: =IF(E4<>"",E4-TODAY(),"") -> 24 | G4: 5 | H4: 35 | I4: =IF(H4<>"",H4-G4,"") -> 30 | J4: Paid | K4: =IF(J4<>"",TODAY(),"") -> 46107 | L4: Renewed | M4: Private | N4: WeChat | O4: 2 | T4: 3 Months | U4: 90
A5: Aymane.chergui.aymanox@gmail.com | B5: chatgpt | C5: 1 Month | D5: 46101 | E5: =IF(C5<>"",D5+VLOOKUP(C5,$T$2:$U$6,2,FALSE),"") -> 46131 | F5: =IF(E5<>"",E5-TODAY(),"") -> 24 | G5: 5 | H5: 35 | I5: =IF(H5<>"",H5-G5,"") -> 30 | J5: Paid | K5: =IF(J5<>"",TODAY(),"") -> 46107 | L5: Renewed | M5: Private | N5: WeChat | O5: 2 | T5: 6 Months | U5: 180
A6: Hassanagoujgal72@gmail.com | B6: canva | C6: 1 Year | D6: 46074 | E6: =IF(C6<>"",D6+VLOOKUP(C6,$T$2:$U$6,2,FALSE),"") -> 46439 | F6: =IF(E6<>"",E6-TODAY(),"") -> 332 | G6: 5 | H6: 60 | I6: =IF(H6<>"",H6-G6,"") -> 55 | J6: Paid | K6: =IF(J6<>"",TODAY(),"") -> 46107 | L6: Renewed | M6: Private | N6: WeChat | T6: 1 Year | U6: 365
A7: pbqepyv99@outlook.com | B7: chatgpt | C7: 1 Year | D7: 46074 | E7: =IF(C7<>"",D7+VLOOKUP(C7,$T$2:$U$6,2,FALSE),"") -> 46439 | F7: =IF(E7<>"",E7-TODAY(),"") -> 332 | G7: 40 | H7: 300 | I7: =IF(H7<>"",H7-G7,"") -> 260 | J7: Paid | K7: =IF(J7<>"",TODAY(),"") -> 46107 | L7: Renewed | M7: Private | N7: WeChat
A8: klvcxsm620@outlook.com | B8: chatgpt | C8: 1 Year | D8: 46074 | E8: =IF(C8<>"",D8+VLOOKUP(C8,$T$2:$U$6,2,FALSE),"") -> 46439 | F8: =IF(E8<>"",E8-TODAY(),"") -> 332 | G8: 40 | H8: 300 | I8: =IF(H8<>"",H8-G8,"") -> 260 | J8: Paid | K8: =IF(J8<>"",TODAY(),"") -> 46107 | L8: Renewed | M8: Private | N8: WeChat
A9: mazforge01@gmail.com | B9: chatgpt | C9: 1 Month | D9: 46074 | E9: =IF(C9<>"",D9+VLOOKUP(C9,$T$2:$U$6,2,FALSE),"") -> 46104 | F9: =IF(E9<>"",E9-TODAY(),"") -> -3 | G9: 5 | H9: 35 | I9: =IF(H9<>"",H9-G9,"") -> 30 | J9: Paid | K9: =IF(J9<>"",TODAY(),"") -> 46107 | L9: Renewed | M9: Private | N9: WeChat
A10: mazforge01@gmail.com | B10: perplexity ai | C10: 1 Month | D10: 46074 | E10: =IF(C10<>"",D10+VLOOKUP(C10,$T$2:$U$6,2,FALSE),"") -> 46104 | F10: =IF(E10<>"",E10-TODAY(),"") -> -3 | G10: 15 | H10: 40 | I10: =IF(H10<>"",H10-G10,"") -> 25 | J10: Paid | K10: =IF(J10<>"",TODAY(),"") -> 46107 | L10: Renewed | M10: Private | N10: WeChat
A11: Artemvolodaskiss@icloud.com | B11: chatgpt | C11: 1 Month | D11: 46100 | E11: =IF(C11<>"",D11+VLOOKUP(C11,$T$2:$U$6,2,FALSE),"") -> 46130 | F11: =IF(E11<>"",E11-TODAY(),"") -> 23 | G11: 5 | H11: 35 | I11: =IF(H11<>"",H11-G11,"") -> 30 | J11: Paid | K11: =IF(J11<>"",TODAY(),"") -> 46107 | L11: Renewed | M11: Private | N11: WeChat | O11: 2
A12: mggg7132@gmail.com | B12: chatgpt | C12: 1 Month | D12: 46100 | E12: =IF(C12<>"",D12+VLOOKUP(C12,$T$2:$U$6,2,FALSE),"") -> 46130 | F12: =IF(E12<>"",E12-TODAY(),"") -> 23 | G12: 5 | H12: 35 | I12: =IF(H12<>"",H12-G12,"") -> 30 | J12: Paid | K12: =IF(J12<>"",TODAY(),"") -> 46107 | L12: Renewed | M12: Private | N12: WeChat | O12: 2
A13: driss.1427@gmail.com | B13: IPTV | C13: 1 Year | D13: 46074 | E13: =IF(C13<>"",D13+VLOOKUP(C13,$T$2:$U$6,2,FALSE),"") -> 46439 | F13: =IF(E13<>"",E13-TODAY(),"") -> 332 | G13: 70 | H13: 200 | I13: =IF(H13<>"",H13-G13,"") -> 130 | J13: Paid | K13: =IF(J13<>"",TODAY(),"") -> 46107 | L13: Renewed | M13: Private | N13: WeChat
A14: Kostyaanna@gmail.com | B14: chatgpt | C14: 1 Month | D14: 46099 | E14: =IF(C14<>"",D14+VLOOKUP(C14,$T$2:$U$6,2,FALSE),"") -> 46129 | F14: =IF(E14<>"",E14-TODAY(),"") -> 22 | G14: 10 | H14: 70 | I14: =IF(H14<>"",H14-G14,"") -> 60 | J14: Paid | K14: =IF(J14<>"",TODAY(),"") -> 46107 | L14: Renewed | M14: Private | N14: WeChat | O14: 2
A15: radzapovakarina020@gmail.com | B15: chatgpt | C15: 1 Month | D15: =D14 -> 46099 | E15: =IF(C15<>"",D15+VLOOKUP(C15,$T$2:$U$6,2,FALSE),"") -> 46129 | F15: =IF(E15<>"",E15-TODAY(),"") -> 22 | G15: 5 | H15: 35 | I15: =IF(H15<>"",H15-G15,"") -> 30 | J15: Paid | K15: =IF(J15<>"",TODAY(),"") -> 46107 | L15: Renewed | M15: Private | N15: WeChat
A16: badr400000@gmail.com | B16: chatgpt | C16: 1 Month | D16: 46076 | E16: =IF(C16<>"",D16+VLOOKUP(C16,$T$2:$U$6,2,FALSE),"") -> 46106 | F16: =IF(E16<>"",E16-TODAY(),"") -> -1 | G16: 5 | H16: 35 | I16: =IF(H16<>"",H16-G16,"") -> 30 | J16: Paid | K16: =IF(J16<>"",TODAY(),"") -> 46107 | L16: Renewed | M16: Private | N16: WeChat
A17: amponsahrichard49@gmail.com | B17: chatgpt | C17: 1 Month | D17: 46076 | E17: =IF(C17<>"",D17+VLOOKUP(C17,$T$2:$U$6,2,FALSE),"") -> 46106 | F17: =IF(E17<>"",E17-TODAY(),"") -> -1 | G17: 5 | H17: 35 | I17: =IF(H17<>"",H17-G17,"") -> 30 | J17: Paid | K17: =IF(J17<>"",TODAY(),"") -> 46107 | L17: Renewed | M17: Private | N17: WeChat
A18: ghalebsaleh221@gmail.com | B18: chatgpt | C18: 1 Month | D18: 46076 | E18: =IF(C18<>"",D18+VLOOKUP(C18,$T$2:$U$6,2,FALSE),"") -> 46106 | F18: =IF(E18<>"",E18-TODAY(),"") -> -1 | G18: 5 | H18: 35 | I18: =IF(H18<>"",H18-G18,"") -> 30 | J18: Paid | K18: =IF(J18<>"",TODAY(),"") -> 46107 | L18: Renewed | M18: Private | N18: WeChat
A19: elmounchitwiame@gmail.com | B19: chatgpt | C19: 1 Month | D19: 46099 | E19: =IF(C19<>"",D19+VLOOKUP(C19,$T$2:$U$6,2,FALSE),"") -> 46129 | F19: =IF(E19<>"",E19-TODAY(),"") -> 22 | G19: 5 | H19: 35 | I19: =IF(H19<>"",H19-G19,"") -> 30 | J19: Paid | K19: =IF(J19<>"",TODAY(),"") -> 46107 | L19: Renewed | M19: Private | N19: WeChat | O19: 2
A20: M.sufyan.bjut@gmail.com | B20: chatgpt | C20: 1 Month | D20: 46094 | E20: =IF(C20<>"",D20+VLOOKUP(C20,$T$2:$U$6,2,FALSE),"") -> 46124 | F20: =IF(E20<>"",E20-TODAY(),"") -> 17 | G20: 5 | H20: 35 | I20: =IF(H20<>"",H20-G20,"") -> 30 | J20: Paid | K20: =IF(J20<>"",TODAY(),"") -> 46107 | L20: Renewed | M20: Private | N20: WeChat
A21: joud.hani08@gmail.com | B21: chatgpt | C21: 1 Month | D21: 46076 | E21: =IF(C21<>"",D21+VLOOKUP(C21,$T$2:$U$6,2,FALSE),"") -> 46106 | F21: =IF(E21<>"",E21-TODAY(),"") -> -1 | G21: 5 | H21: 35 | I21: =IF(H21<>"",H21-G21,"") -> 30 | J21: Paid | K21: =IF(J21<>"",TODAY(),"") -> 46107 | L21: Renewed | M21: Private | N21: WeChat
A22: bakrazaroual@icloud.com | B22: VPN | C22: 1 Year | D22: 46076 | E22: =IF(C22<>"",D22+VLOOKUP(C22,$T$2:$U$6,2,FALSE),"") -> 46441 | F22: =IF(E22<>"",E22-TODAY(),"") -> 334 | G22: 20 | H22: 200 | I22: =IF(H22<>"",H22-G22,"") -> 180 | J22: Paid | K22: =IF(J22<>"",TODAY(),"") -> 46107 | L22: Renewed | M22: Private | N22: WeChat
A23: bakrazaroual@icloud.com | B23: NETFLIX | C23: 1 Month | D23: 46101 | E23: =IF(C23<>"",D23+VLOOKUP(C23,$T$2:$U$6,2,FALSE),"") -> 46131 | F23: =IF(E23<>"",E23-TODAY(),"") -> 24 | G23: 18 | H23: 30 | I23: =IF(H23<>"",H23-G23,"") -> 12 | J23: Paid | K23: =IF(J23<>"",TODAY(),"") -> 46107 | L23: Renewed | M23: Shared | N23: WeChat | O23: 2
A24: wassim.sania19@gmail.com | B24: chatgpt | C24: 1 Month | D24: 46076 | E24: =IF(C24<>"",D24+VLOOKUP(C24,$T$2:$U$6,2,FALSE),"") -> 46106 | F24: =IF(E24<>"",E24-TODAY(),"") -> -1 | G24: 5 | H24: 35 | I24: =IF(H24<>"",H24-G24,"") -> 30 | J24: Paid | K24: =IF(J24<>"",TODAY(),"") -> 46107 | L24: Renewed | M24: Private | N24: WeChat
A25: fatohe.27@gmail.com | B25: chatgpt | C25: 1 Month | D25: 46076 | E25: =IF(C25<>"",D25+VLOOKUP(C25,$T$2:$U$6,2,FALSE),"") -> 46106 | F25: =IF(E25<>"",E25-TODAY(),"") -> -1 | G25: 5 | H25: 35 | I25: =IF(H25<>"",H25-G25,"") -> 30 | J25: Paid | K25: =IF(J25<>"",TODAY(),"") -> 46107 | L25: Renewed | M25: Private | N25: WeChat
A26: engr.mustafatahir@gmail.com | B26: chatgpt | C26: 1 Month | D26: 46103 | E26: =IF(C26<>"",D26+VLOOKUP(C26,$T$2:$U$6,2,FALSE),"") -> 46133 | F26: =IF(E26<>"",E26-TODAY(),"") -> 26 | G26: 5 | H26: 35 | I26: =IF(H26<>"",H26-G26,"") -> 30 | J26: Paid | K26: =IF(J26<>"",TODAY(),"") -> 46107 | L26: Renewed | M26: Private | N26: WeChat | O26: 2
A27: mounib.bouabid2012@gmail.com | B27: chatgpt | C27: 1 Month | D27: 46076 | E27: =IF(C27<>"",D27+VLOOKUP(C27,$T$2:$U$6,2,FALSE),"") -> 46106 | F27: =IF(E27<>"",E27-TODAY(),"") -> -1 | G27: 5 | H27: 35 | I27: =IF(H27<>"",H27-G27,"") -> 30 | J27: Paid | K27: =IF(J27<>"",TODAY(),"") -> 46107 | L27: Renewed | M27: Private | N27: WeChat
A28: etudescn1@gmail.com | B28: chatgpt | C28: 1 Month | D28: 46076 | E28: =IF(C28<>"",D28+VLOOKUP(C28,$T$2:$U$6,2,FALSE),"") -> 46106 | F28: =IF(E28<>"",E28-TODAY(),"") -> -1 | G28: 5 | H28: 35 | I28: =IF(H28<>"",H28-G28,"") -> 30 | J28: Paid | K28: =IF(J28<>"",TODAY(),"") -> 46107 | L28: Renewed | M28: Private | N28: WeChat
A29: rachahaziz2@gmail.com | B29: chatgpt | C29: 1 Month | D29: 46076 | E29: =IF(C29<>"",D29+VLOOKUP(C29,$T$2:$U$6,2,FALSE),"") -> 46106 | F29: =IF(E29<>"",E29-TODAY(),"") -> -1 | G29: 5 | H29: 35 | I29: =IF(H29<>"",H29-G29,"") -> 30 | J29: Paid | K29: =IF(J29<>"",TODAY(),"") -> 46107 | L29: Renewed | M29: Private | N29: WeChat
A30: chamunokara70@gmail.com | B30: chatgpt | C30: 1 Month | D30: 46103 | E30: =IF(C30<>"",D30+VLOOKUP(C30,$T$2:$U$6,2,FALSE),"") -> 46133 | F30: =IF(E30<>"",E30-TODAY(),"") -> 26 | G30: 5 | H30: 35 | I30: =IF(H30<>"",H30-G30,"") -> 30 | J30: Paid | K30: =IF(J30<>"",TODAY(),"") -> 46107 | L30: Renewed | M30: Private | N30: WeChat | O30: 2
A31: Sakinemouha@gmail.com | B31: VPN | C31: 1 Month | D31: 46076 | E31: =IF(C31<>"",D31+VLOOKUP(C31,$T$2:$U$6,2,FALSE),"") -> 46106 | F31: =IF(E31<>"",E31-TODAY(),"") -> -1 | G31: 5 | H31: 35 | I31: =IF(H31<>"",H31-G31,"") -> 30 | J31: Paid | K31: =IF(J31<>"",TODAY(),"") -> 46107 | L31: Renewed | M31: Private | N31: WeChat
A32: bibekbamanu1@gmail.com | B32: chatgpt | C32: 1 Month | D32: 46101 | E32: =IF(C32<>"",D32+VLOOKUP(C32,$T$2:$U$6,2,FALSE),"") -> 46131 | F32: =IF(E32<>"",E32-TODAY(),"") -> 24 | G32: 5 | H32: 35 | I32: =IF(H32<>"",H32-G32,"") -> 30 | J32: Paid | K32: =IF(J32<>"",TODAY(),"") -> 46107 | L32: Renewed | M32: Private | N32: WeChat | O32: 2
A33: hindelkarrichi@gmail.com | B33: chatgpt | C33: 1 Month | D33: =IF(C33<>"",TODAY(),"") -> 46107 | E33: =IF(C33<>"",D33+VLOOKUP(C33,$T$2:$U$6,2,FALSE),"") -> 46137 | F33: =IF(E33<>"",E33-TODAY(),"") -> 30 | G33: 5 | H33: 35 | I33: =IF(H33<>"",H33-G33,"") -> 30 | J33: Paid | K33: =IF(J33<>"",TODAY(),"") -> 46107 | L33: Renewed | M33: Private | N33: WeChat
A34: asikpojessica@gmail.com | B34: chatgpt | C34: 1 Month | D34: =IF(C34<>"",TODAY(),"") -> 46107 | E34: =IF(C34<>"",D34+VLOOKUP(C34,$T$2:$U$6,2,FALSE),"") -> 46137 | F34: =IF(E34<>"",E34-TODAY(),"") -> 30 | G34: 5 | H34: 35 | I34: =IF(H34<>"",H34-G34,"") -> 30 | J34: Paid | K34: =IF(J34<>"",TODAY(),"") -> 46107 | L34: Renewed | M34: Private | N34: WeChat
A35: younglily4real@gmail.com | B35: chatgpt | C35: 1 Month | D35: =IF(C35<>"",TODAY(),"") -> 46107 | E35: =IF(C35<>"",D35+VLOOKUP(C35,$T$2:$U$6,2,FALSE),"") -> 46137 | F35: =IF(E35<>"",E35-TODAY(),"") -> 30 | G35: 5 | H35: 35 | I35: =IF(H35<>"",H35-G35,"") -> 30 | J35: Paid | K35: =IF(J35<>"",TODAY(),"") -> 46107 | L35: Renewed | M35: Private | N35: WeChat
A36: 4u4me77@gmail.com | B36: chatgpt | C36: 1 Month | D36: =IF(C36<>"",TODAY(),"") -> 46107 | E36: =IF(C36<>"",D36+VLOOKUP(C36,$T$2:$U$6,2,FALSE),"") -> 46137 | F36: =IF(E36<>"",E36-TODAY(),"") -> 30 | G36: 5 | H36: 35 | I36: =IF(H36<>"",H36-G36,"") -> 30 | J36: Paid | K36: =IF(J36<>"",TODAY(),"") -> 46107 | L36: Renewed | M36: Private | N36: WeChat
A37: buehsamuel81@gmail.com | B37: chatgpt | C37: 1 Month | D37: =IF(C37<>"",TODAY(),"") -> 46107 | E37: =IF(C37<>"",D37+VLOOKUP(C37,$T$2:$U$6,2,FALSE),"") -> 46137 | F37: =IF(E37<>"",E37-TODAY(),"") -> 30 | G37: 5 | H37: 35 | I37: =IF(H37<>"",H37-G37,"") -> 30 | J37: Paid | K37: =IF(J37<>"",TODAY(),"") -> 46107 | L37: Renewed | M37: Private | N37: WeChat
A38: Bendalhsaadeddine001@gmail.com | B38: chatgpt | C38: 1 Month | D38: =IF(C38<>"",TODAY(),"") -> 46107 | E38: =IF(C38<>"",D38+VLOOKUP(C38,$T$2:$U$6,2,FALSE),"") -> 46137 | F38: =IF(E38<>"",E38-TODAY(),"") -> 30 | G38: 5 | H38: 35 | I38: =IF(H38<>"",H38-G38,"") -> 30 | J38: Paid | K38: =IF(J38<>"",TODAY(),"") -> 46107 | L38: Renewed | M38: Private | N38: WeChat
A39: usama.crlm10@gmail.com | B39: chatgpt | C39: 1 Month | D39: =IF(C39<>"",TODAY(),"") -> 46107 | E39: =IF(C39<>"",D39+VLOOKUP(C39,$T$2:$U$6,2,FALSE),"") -> 46137 | F39: =IF(E39<>"",E39-TODAY(),"") -> 30 | G39: 5 | H39: 35 | I39: =IF(H39<>"",H39-G39,"") -> 30 | J39: Pending | K39: =IF(J39<>"",TODAY(),"") -> 46107 | L39: Renewed | M39: Private | N39: WeChat | O39: 2
A40: yassminayassmina759@gmail.com | B40: NETFLIX | C40: 1 Month | D40: 46075 | E40: =IF(C40<>"",D40+VLOOKUP(C40,$T$2:$U$6,2,FALSE),"") -> 46105 | F40: =IF(E40<>"",E40-TODAY(),"") -> -2 | G40: 18 | H40: 30 | I40: =IF(H40<>"",H40-G40,"") -> 12 | J40: Paid | K40: =IF(J40<>"",TODAY(),"") -> 46107 | L40: Renewed | M40: Shared | N40: WeChat
A41: a.h.binothman88@gmail.com | B41: chatgpt | C41: 1 Month | D41: 46077 | E41: =IF(C41<>"",D41+VLOOKUP(C41,$T$2:$U$6,2,FALSE),"") -> 46107 | F41: =IF(E41<>"",E41-TODAY(),"") -> 0 | G41: 5 | H41: 35 | I41: =IF(H41<>"",H41-G41,"") -> 30 | J41: Paid | K41: =IF(J41<>"",TODAY(),"") -> 46107 | L41: Renewed | M41: Private | N41: WeChat
A42: yassine.flto12@gmail.com | B42: chatgpt | C42: 1 Month | D42: 46104 | E42: =IF(C42<>"",D42+VLOOKUP(C42,$T$2:$U$6,2,FALSE),"") -> 46134 | F42: =IF(E42<>"",E42-TODAY(),"") -> 27 | G42: 5 | H42: 35 | I42: =IF(H42<>"",H42-G42,"") -> 30 | J42: Paid | K42: =IF(J42<>"",TODAY(),"") -> 46107 | L42: Renewed | M42: Private | N42: WeChat | O42: 2
A43: lakssirwalid@gmail.com | B43: chatgpt | C43: 1 Month | D43: 46077 | E43: =IF(C43<>"",D43+VLOOKUP(C43,$T$2:$U$6,2,FALSE),"") -> 46107 | F43: =IF(E43<>"",E43-TODAY(),"") -> 0 | G43: 5 | H43: 35 | I43: =IF(H43<>"",H43-G43,"") -> 30 | J43: Paid | K43: =IF(J43<>"",TODAY(),"") -> 46107 | L43: Renewed | M43: Private | N43: WeChat
A44: kkzahia@gmail.com | B44: chatgpt | C44: 1 Month | D44: 46077 | E44: =IF(C44<>"",D44+VLOOKUP(C44,$T$2:$U$6,2,FALSE),"") -> 46107 | F44: =IF(E44<>"",E44-TODAY(),"") -> 0 | G44: 5 | H44: 35 | I44: =IF(H44<>"",H44-G44,"") -> 30 | J44: Paid | K44: =IF(J44<>"",TODAY(),"") -> 46107 | L44: Renewed | M44: Private | N44: WeChat
A45: izmalkova518@gmail.com | B45: chatgpt | C45: 1 Month | D45: 46105 | E45: =IF(C45<>"",D45+VLOOKUP(C45,$T$2:$U$6,2,FALSE),"") -> 46135 | F45: =IF(E45<>"",E45-TODAY(),"") -> 28 | G45: 5 | H45: 35 | I45: =IF(H45<>"",H45-G45,"") -> 30 | J45: Paid | K45: =IF(J45<>"",TODAY(),"") -> 46107 | L45: Renewed | M45: Private | N45: WeChat | O45: 2
A46: vitaliiuchunzhan@gmail.com | B46: chatgpt | C46: 1 Month | D46: 46105 | E46: =IF(C46<>"",D46+VLOOKUP(C46,$T$2:$U$6,2,FALSE),"") -> 46135 | F46: =IF(E46<>"",E46-TODAY(),"") -> 28 | G46: 5 | H46: 35 | I46: =IF(H46<>"",H46-G46,"") -> 30 | J46: Paid | K46: =IF(J46<>"",TODAY(),"") -> 46107 | L46: Renewed | M46: Private | N46: WeChat | O46: 2
A47: alsaqqaf200@gmail.com | B47: chatgpt+gemini | C47: 1 Month | D47: 46099 | E47: =IF(C47<>"",D47+VLOOKUP(C47,$T$2:$U$6,2,FALSE),"") -> 46129 | F47: =IF(E47<>"",E47-TODAY(),"") -> 22 | G47: 15 | H47: 85 | I47: =IF(H47<>"",H47-G47,"") -> 70 | J47: Paid | K47: =IF(J47<>"",TODAY(),"") -> 46107 | L47: Renewed | M47: Private | N47: WeChat | O47: 2
A48: elyassaamohamed43@gmail.com | B48: chatgpt | C48: 1 Month | D48: 46072 | E48: =IF(C48<>"",D48+VLOOKUP(C48,$T$2:$U$6,2,FALSE),"") -> 46102 | F48: =IF(E48<>"",E48-TODAY(),"") -> -5 | G48: 5 | H48: 35 | I48: =IF(H48<>"",H48-G48,"") -> 30 | J48: Paid | K48: =IF(J48<>"",TODAY(),"") -> 46107 | L48: Renewed | M48: Private | N48: WeChat
A49: alizpcmsiesta1@gmail.com | B49: chatgpt | C49: 1 Month | D49: 46099 | E49: =IF(C49<>"",D49+VLOOKUP(C49,$T$2:$U$6,2,FALSE),"") -> 46129 | F49: =IF(E49<>"",E49-TODAY(),"") -> 22 | G49: 10 | H49: 70 | I49: =IF(H49<>"",H49-G49,"") -> 60 | J49: Paid | K49: =IF(J49<>"",TODAY(),"") -> 46107 | L49: Renewed | M49: Private | N49: WeChat | O49: 2
A50: radzapovakarina020@gmail.com | B50: chatgpt | C50: 1 Month | D50: 46099 | E50: =IF(C50<>"",D50+VLOOKUP(C50,$T$2:$U$6,2,FALSE),"") -> 46129 | F50: =IF(E50<>"",E50-TODAY(),"") -> 22 | G50: 10 | H50: 70 | I50: =IF(H50<>"",H50-G50,"") -> 60 | J50: Paid | K50: =IF(J50<>"",TODAY(),"") -> 46107 | L50: Renewed | M50: Private | N50: WeChat | O50: 2
A51: Malikahou12@gmail.com | B51: VPN | C51: 1 Month | D51: 46077 | E51: =IF(C51<>"",D51+VLOOKUP(C51,$T$2:$U$6,2,FALSE),"") -> 46107 | F51: =IF(E51<>"",E51-TODAY(),"") -> 0 | G51: 5 | H51: 25 | I51: =IF(H51<>"",H51-G51,"") -> 20 | J51: Paid | K51: =IF(J51<>"",TODAY(),"") -> 46107 | L51: Renewed | M51: Private | N51: WeChat
A52: Vieadam007@gmail.com | B52: NETFLIX | C52: 1 Month | D52: 46078 | E52: =IF(C52<>"",D52+VLOOKUP(C52,$T$2:$U$6,2,FALSE),"") -> 46108 | F52: =IF(E52<>"",E52-TODAY(),"") -> 1 | G52: 18 | H52: 35 | I52: =IF(H52<>"",H52-G52,"") -> 17 | J52: Paid | K52: =IF(J52<>"",TODAY(),"") -> 46107 | L52: Renewed | M52: Private | N52: WeChat
A53: akid.imanne@gmail.com | B53: chatgpt | C53: 1 Month | D53: 46078 | E53: =IF(C53<>"",D53+VLOOKUP(C53,$T$2:$U$6,2,FALSE),"") -> 46108 | F53: =IF(E53<>"",E53-TODAY(),"") -> 1 | G53: 5 | H53: 35 | I53: =IF(H53<>"",H53-G53,"") -> 30 | J53: Paid | K53: =IF(J53<>"",TODAY(),"") -> 46107 | L53: Renewed | M53: Private | N53: WeChat
A54: mekontchousteve059@gmail.com | B54: chatgpt | C54: 1 Month | D54: 46078 | E54: =IF(C54<>"",D54+VLOOKUP(C54,$T$2:$U$6,2,FALSE),"") -> 46108 | F54: =IF(E54<>"",E54-TODAY(),"") -> 1 | G54: 5 | H54: 35 | I54: =IF(H54<>"",H54-G54,"") -> 30 | J54: Paid | K54: =IF(J54<>"",TODAY(),"") -> 46107 | L54: Renewed | M54: Private | N54: WeChat
A55: anup100653@gmail.com | B55: chatgpt | C55: 1 Month | D55: 46078 | E55: =IF(C55<>"",D55+VLOOKUP(C55,$T$2:$U$6,2,FALSE),"") -> 46108 | F55: =IF(E55<>"",E55-TODAY(),"") -> 1 | G55: 5 | H55: 35 | I55: =IF(H55<>"",H55-G55,"") -> 30 | J55: Paid | K55: =IF(J55<>"",TODAY(),"") -> 46107 | L55: Renewed | M55: Private | N55: WeChat
A56: marwane.rako@gmail.com | B56: chatgpt | C56: 1 Month | D56: 46079 | E56: =IF(C56<>"",D56+VLOOKUP(C56,$T$2:$U$6,2,FALSE),"") -> 46109 | F56: =IF(E56<>"",E56-TODAY(),"") -> 2 | G56: 5 | H56: 35 | I56: =IF(H56<>"",H56-G56,"") -> 30 | J56: Paid | K56: =IF(J56<>"",TODAY(),"") -> 46107 | L56: Renewed | M56: Private | N56: WeChat
A57: mekontchousteve059@gmail.com | B57: chatgpt | C57: 1 Month | D57: 46079 | E57: =IF(C57<>"",D57+VLOOKUP(C57,$T$2:$U$6,2,FALSE),"") -> 46109 | F57: =IF(E57<>"",E57-TODAY(),"") -> 2 | G57: 5 | H57: 35 | I57: =IF(H57<>"",H57-G57,"") -> 30 | J57: Paid | K57: =IF(J57<>"",TODAY(),"") -> 46107 | L57: Renewed | M57: Private | N57: WeChat
A58: mohamedzouad1974@gmail.com | B58: chatgpt | C58: 1 Month | D58: 46079 | E58: =IF(C58<>"",D58+VLOOKUP(C58,$T$2:$U$6,2,FALSE),"") -> 46109 | F58: =IF(E58<>"",E58-TODAY(),"") -> 2 | G58: 5 | H58: 35 | I58: =IF(H58<>"",H58-G58,"") -> 30 | J58: Paid | K58: =IF(J58<>"",TODAY(),"") -> 46107 | L58: Renewed | M58: Private | N58: WeChat
A59: vitaliiuchunzhan@gmail.com | B59: chatgpt | C59: 1 Month | D59: 46079 | E59: =IF(C59<>"",D59+VLOOKUP(C59,$T$2:$U$6,2,FALSE),"") -> 46109 | F59: =IF(E59<>"",E59-TODAY(),"") -> 2 | G59: 5 | H59: 35 | I59: =IF(H59<>"",H59-G59,"") -> 30 | J59: Paid | K59: =IF(J59<>"",TODAY(),"") -> 46107 | L59: Renewed | M59: Private | N59: WeChat
A60: izmalkova518@gmail.com | B60: chatgpt | C60: 1 Month | D60: 46079 | E60: =IF(C60<>"",D60+VLOOKUP(C60,$T$2:$U$6,2,FALSE),"") -> 46109 | F60: =IF(E60<>"",E60-TODAY(),"") -> 2 | G60: 5 | H60: 35 | I60: =IF(H60<>"",H60-G60,"") -> 30 | J60: Paid | K60: =IF(J60<>"",TODAY(),"") -> 46107 | L60: Renewed | M60: Private | N60: WeChat
A61: nourddintaibi26@gmail.com | B61: chatgpt | C61: 1 Month | D61: 46079 | E61: =IF(C61<>"",D61+VLOOKUP(C61,$T$2:$U$6,2,FALSE),"") -> 46109 | F61: =IF(E61<>"",E61-TODAY(),"") -> 2 | G61: 5 | H61: 35 | I61: =IF(H61<>"",H61-G61,"") -> 30 | J61: Paid | K61: =IF(J61<>"",TODAY(),"") -> 46107 | L61: Renewed | M61: Private | N61: WeChat
A62: Richardjun237@gmail.com | B62: chatgpt | C62: 1 Month | D62: 46079 | E62: =IF(C62<>"",D62+VLOOKUP(C62,$T$2:$U$6,2,FALSE),"") -> 46109 | F62: =IF(E62<>"",E62-TODAY(),"") -> 2 | G62: 5 | H62: 35 | I62: =IF(H62<>"",H62-G62,"") -> 30 | J62: Paid | K62: =IF(J62<>"",TODAY(),"") -> 46107 | L62: Renewed | M62: Private | N62: WeChat
... A118: engrmuhammadwaqas88@gmail.com | B118: gemini+chatgpt | C118: 1 Month | D118: 46085 | E118: =IF(C118<>"",D118+VLOOKUP(C118,$T$2:$U$6,2,FALSE),"") -> 46115 | F118: =IF(E118<>"",E118-TODAY(),"") -> 8 | G118: 10 | H118: 50 | I118: =IF(H118<>"",H118-G118,"") -> 40 | J118: Paid | K118: =IF(J118<>"",TODAY(),"") -> 46107 | L118: Renewed | M118: Private | N118: WeChat
A119: nisgoran@gmail.com | B119: gemini+chatgpt | C119: 1 Month | D119: 46085 | E119: =IF(C119<>"",D119+VLOOKUP(C119,$T$2:$U$6,2,FALSE),"") -> 46115 | F119: =IF(E119<>"",E119-TODAY(),"") -> 8 | G119: 10 | H119: 50 | I119: =IF(H119<>"",H119-G119,"") -> 40 | J119: Paid | K119: 46085 | L119: Renewed | M119: Private | N119: WeChat
A120: alexlusambya58@gmail.com | B120: chatgpt | C120: 1 Month | D120: 46085 | E120: =IF(C120<>"",D120+VLOOKUP(C120,$T$2:$U$6,2,FALSE),"") -> 46115 | F120: =IF(E120<>"",E120-TODAY(),"") -> 8 | G120: 5 | H120: 35 | I120: =IF(H120<>"",H120-G120,"") -> 30 | J120: Paid | K120: 46085 | L120: Renewed | M120: Private | N120: WeChat
A121: aybekmamurow@gmail.com | B121: chatgpt | C121: 1 Month | D121: 46085 | E121: =IF(C121<>"",D121+VLOOKUP(C121,$T$2:$U$6,2,FALSE),"") -> 46115 | F121: =IF(E121<>"",E121-TODAY(),"") -> 8 | G121: 5 | H121: 35 | I121: =IF(H121<>"",H121-G121,"") -> 30 | J121: Paid | K121: 46085 | L121: Renewed | M121: Private | N121: WeChat
A122: Oussamasami872@gmail.com | B122: chatgpt | C122: 1 Month | D122: 46085 | E122: =IF(C122<>"",D122+VLOOKUP(C122,$T$2:$U$6,2,FALSE),"") -> 46115 | F122: =IF(E122<>"",E122-TODAY(),"") -> 8 | G122: 5 | H122: 35 | I122: =IF(H122<>"",H122-G122,"") -> 30 | J122: CANCELED | K122: 46085 | L122: Renewed | M122: Private | N122: WeChat
A123: artiquo381@gmail.com | B123: chatgpt | C123: 1 Month | D123: 46086 | E123: =IF(C123<>"",D123+VLOOKUP(C123,$T$2:$U$6,2,FALSE),"") -> 46116 | F123: =IF(E123<>"",E123-TODAY(),"") -> 9 | G123: 5 | H123: 35 | I123: =IF(H123<>"",H123-G123,"") -> 30 | J123: Paid | K123: 46085 | L123: Renewed | M123: Private | N123: WeChat
A124: samreenarasheed39@gmail.com | B124: chatgpt | C124: 1 Month | D124: 46085 | E124: =IF(C124<>"",D124+VLOOKUP(C124,$T$2:$U$6,2,FALSE),"") -> 46115 | F124: =IF(E124<>"",E124-TODAY(),"") -> 8 | G124: 5 | H124: 35 | I124: =IF(H124<>"",H124-G124,"") -> 30 | J124: Paid | K124: 46085 | L124: Renewed | M124: Private | N124: WeChat
A125: derraouihamza1@gmail.com | B125: chatgpt | C125: 1 Month | D125: 46085 | E125: =IF(C125<>"",D125+VLOOKUP(C125,$T$2:$U$6,2,FALSE),"") -> 46115 | F125: =IF(E125<>"",E125-TODAY(),"") -> 8 | G125: 5 | H125: 35 | I125: =IF(H125<>"",H125-G125,"") -> 30 | J125: Paid | K125: 46085 | L125: Renewed | M125: Private | N125: WeChat
A126: milimarley70@gmail.com | B126: chatgpt | C126: 1 Month | D126: 46085 | E126: =IF(C126<>"",D126+VLOOKUP(C126,$T$2:$U$6,2,FALSE),"") -> 46115 | F126: =IF(E126<>"",E126-TODAY(),"") -> 8 | G126: 5 | H126: 35 | I126: =IF(H126<>"",H126-G126,"") -> 30 | J126: Paid | K126: 46085 | L126: Renewed | M126: Private | N126: WeChat
A127: Sounayassir24@gmail.com | B127: chatgpt | C127: 1 Month | D127: 46085 | E127: =IF(C127<>"",D127+VLOOKUP(C127,$T$2:$U$6,2,FALSE),"") -> 46115 | F127: =IF(E127<>"",E127-TODAY(),"") -> 8 | G127: 5 | H127: 35 | I127: =IF(H127<>"",H127-G127,"") -> 30 | J127: CANCELED | K127: 46085 | L127: Renewed | M127: Private | N127: WeChat
A128: mdzunaed.17@gmail.com | B128: chatgpt | C128: 1 Month | D128: 46085 | E128: =IF(C128<>"",D128+VLOOKUP(C128,$T$2:$U$6,2,FALSE),"") -> 46115 | F128: =IF(E128<>"",E128-TODAY(),"") -> 8 | G128: 5 | H128: 35 | I128: =IF(H128<>"",H128-G128,"") -> 30 | J128: Paid | K128: 46085 | L128: Renewed | M128: Private | N128: WeChat
A129: john.ibdp@gmail.com | B129: chatgpt | C129: 1 Month | D129: 46085 | E129: =IF(C129<>"",D129+VLOOKUP(C129,$T$2:$U$6,2,FALSE),"") -> 46115 | F129: =IF(E129<>"",E129-TODAY(),"") -> 8 | G129: 5 | H129: 35 | I129: =IF(H129<>"",H129-G129,"") -> 30 | J129: Paid | K129: 46086 | L129: Renewed | M129: Private | N129: WeChat
A130: hadiriayman3@gmail.com | B130: chatgpt | C130: 1 Month | D130: 46085 | E130: =IF(C130<>"",D130+VLOOKUP(C130,$T$2:$U$6,2,FALSE),"") -> 46115 | F130: =IF(E130<>"",E130-TODAY(),"") -> 8 | G130: 5 | H130: 35 | I130: =IF(H130<>"",H130-G130,"") -> 30 | J130: Paid | K130: 46086 | L130: Renewed | M130: Private | N130: WeChat
... A162: marcussepo1998@gmail.com | B162: chatgpt | C162: 1 Month | D162: 46088 | E162: =IF(C162<>"",D162+VLOOKUP(C162,$T$2:$U$6,2,FALSE),"") -> 46118 | F162: =IF(E162<>"",E162-TODAY(),"") -> 11 | G162: 5 | H162: 35 | I162: =IF(H162<>"",H162-G162,"") -> 30 | J162: Paid | K162: 46087 | L162: Renewed | M162: Private | N162: WeChat
B163: chatgpt | C163: 1 Month | D163: 46088 | E163: =IF(C163<>"",D163+VLOOKUP(C163,$T$2:$U$6,2,FALSE),"") -> 46118 | F163: =IF(E163<>"",E163-TODAY(),"") -> 11 | G163: 5 | H163: 35 | I163: =IF(H163<>"",H163-G163,"") -> 30 | J163: Paid | K163: 46087 | L163: Renewed | M163: Private | N163: WeChat
A164: anajjardouaa@gmail.com | B164: chatgpt | C164: 1 Month | D164: 46088 | E164: =IF(C164<>"",D164+VLOOKUP(C164,$T$2:$U$6,2,FALSE),"") -> 46118 | F164: =IF(E164<>"",E164-TODAY(),"") -> 11 | G164: 5 | H164: 35 | I164: =IF(H164<>"",H164-G164,"") -> 30 | J164: Paid | K164: 46087 | L164: Renewed | M164: Private | N164: WeChat
A165: patient.mah@gmail.com | B165: chatgpt | C165: 1 Month | D165: 46088 | E165: =IF(C165<>"",D165+VLOOKUP(C165,$T$2:$U$6,2,FALSE),"") -> 46118 | F165: =IF(E165<>"",E165-TODAY(),"") -> 11 | G165: 5 | H165: 35 | I165: =IF(H165<>"",H165-G165,"") -> 30 | J165: Paid | K165: 46087 | L165: Renewed | M165: Private | N165: WeChat
A166: Mkisserabab15@gmail.com | B166: chatgpt | C166: 1 Month | D166: 46088 | E166: =IF(C166<>"",D166+VLOOKUP(C166,$T$2:$U$6,2,FALSE),"") -> 46118 | F166: =IF(E166<>"",E166-TODAY(),"") -> 11 | G166: 5 | H166: 35 | I166: =IF(H166<>"",H166-G166,"") -> 30 | J166: Paid | K166: 46087 | L166: Renewed | M166: Private | N166: WeChat
A167: mohammedjaban6@gmail.com | B167: VPN | C167: 3 Months | D167: 46088 | E167: =IF(C167<>"",D167+VLOOKUP(C167,$T$2:$U$6,2,FALSE),"") -> 46178 | F167: =IF(E167<>"",E167-TODAY(),"") -> 71 | G167: 10 | H167: 70 | I167: =IF(H167<>"",H167-G167,"") -> 60 | J167: Paid | K167: 46088 | L167: Renewed | M167: Private | N167: WeChat
A168: bouabid153.live@gmail.com | B168: chatgpt | C168: 3 Months | D168: 46088 | E168: =IF(C168<>"",D168+VLOOKUP(C168,$T$2:$U$6,2,FALSE),"") -> 46178 | F168: =IF(E168<>"",E168-TODAY(),"") -> 71 | G168: 15 | H168: 100 | I168: =IF(H168<>"",H168-G168,"") -> 85 | J168: Paid | K168: 46087 | L168: Renewed | M168: Private | N168: WeChat
A169: chaabimohamed995@gmail.com | B169: chatgpt | C169: 1 Month | D169: 46088 | E169: =IF(C169<>"",D169+VLOOKUP(C169,$T$2:$U$6,2,FALSE),"") -> 46118 | F169: =IF(E169<>"",E169-TODAY(),"") -> 11 | G169: 5 | H169: 35 | I169: =IF(H169<>"",H169-G169,"") -> 30 | J169: Paid | K169: 46087 | L169: Renewed | M169: Private | N169: WeChat
A170: waheed.seu6077@gmail.com | B170: chatgpt | C170: 1 Month | D170: 46088 | E170: =IF(C170<>"",D170+VLOOKUP(C170,$T$2:$U$6,2,FALSE),"") -> 46118 | F170: =IF(E170<>"",E170-TODAY(),"") -> 11 | G170: 5 | H170: 35 | I170: =IF(H170<>"",H170-G170,"") -> 30 | J170: Paid | K170: 46087 | L170: Renewed | M170: Private | N170: WeChat
A171: Mkisserabab15@gmail.com | B171: chatgpt | C171: 1 Month | D171: 46088 | E171: =IF(C171<>"",D171+VLOOKUP(C171,$T$2:$U$6,2,FALSE),"") -> 46118 | F171: =IF(E171<>"",E171-TODAY(),"") -> 11 | G171: 5 | H171: 35 | I171: =IF(H171<>"",H171-G171,"") -> 30 | J171: Paid | K171: 46087 | L171: Renewed | M171: Private | N171: WeChat
A172: shehzad.stu@gmail.com | B172: gemini+chatgpt | C172: 1 Month | D172: 46089 | E172: =IF(C172<>"",D172+VLOOKUP(C172,$T$2:$U$6,2,FALSE),"") -> 46119 | F172: =IF(E172<>"",E172-TODAY(),"") -> 12 | G172: 10 | H172: 50 | I172: =IF(H172<>"",H172-G172,"") -> 40 | J172: Paid | K172: 46089 | L172: Renewed | M172: Private | N172: WeChat
A173: wiammeslahi@gmail.com | B173: chatgpt | C173: 1 Month | D173: 46089 | E173: =IF(C173<>"",D173+VLOOKUP(C173,$T$2:$U$6,2,FALSE),"") -> 46119 | F173: =IF(E173<>"",E173-TODAY(),"") -> 12 | G173: 5 | H173: 35 | I173: =IF(H173<>"",H173-G173,"") -> 30 | J173: Paid | K173: 46087 | L173: Renewed | M173: Private | N173: WeChat
A174: ayamadlom4@gmail.com | B174: chatgpt | C174: 1 Month | D174: 46090 | E174: =IF(C174<>"",D174+VLOOKUP(C174,$T$2:$U$6,2,FALSE),"") -> 46120 | F174: =IF(E174<>"",E174-TODAY(),"") -> 13 | G174: 5 | H174: 35 | I174: =IF(H174<>"",H174-G174,"") -> 30 | J174: Paid | K174: 46087 | L174: Renewed | M174: Private | N174: WeChat
A175: nimanourizadeh80@gmail.com | B175: chatgpt | C175: 1 Month | D175: 46090 | E175: =IF(C175<>"",D175+VLOOKUP(C175,$T$2:$U$6,2,FALSE),"") -> 46120 | F175: =IF(E175<>"",E175-TODAY(),"") -> 13 | G175: 5 | H175: 35 | I175: =IF(H175<>"",H175-G175,"") -> 30 | J175: Paid | K175: 46087 | L175: Renewed | M175: Private | N175: WeChat
... A182: ettrachlimaissame@gmail.com | B182: chatgpt | C182: 1 Month | D182: 46091 | E182: =IF(C182<>"",D182+VLOOKUP(C182,$T$2:$U$6,2,FALSE),"") -> 46121 | F182: =IF(E182<>"",E182-TODAY(),"") -> 14 | G182: 5 | H182: 35 | I182: =IF(H182<>"",H182-G182,"") -> 30 | J182: Paid | K182: 46087 | L182: Renewed | M182: Private | N182: WeChat
A183: betiimes@gmail.com | B183: canva | C183: 1 Year | D183: 46091 | E183: =IF(C183<>"",D183+VLOOKUP(C183,$T$2:$U$6,2,FALSE),"") -> 46456 | F183: =IF(E183<>"",E183-TODAY(),"") -> 349 | G183: 5 | H183: 60 | I183: =IF(H183<>"",H183-G183,"") -> 55 | J183: Paid
A184: engrafaq8373@gmail.com | B184: perplexity ai | C184: 1 Year | D184: 46091 | E184: =IF(C184<>"",D184+VLOOKUP(C184,$T$2:$U$6,2,FALSE),"") -> 46456 | F184: =IF(E184<>"",E184-TODAY(),"") -> 349 | G184: 20 | H184: 250 | I184: =IF(H184<>"",H184-G184,"") -> 230 | J184: Paid | K184: 46091 | L184: Renewed | M184: Private | N184: WeChat
A185: mansoormajad@gmail.com | B185: chatgpt | C185: 1 Month | D185: 46091 | E185: =IF(C185<>"",D185+VLOOKUP(C185,$T$2:$U$6,2,FALSE),"") -> 46121 | F185: =IF(E185<>"",E185-TODAY(),"") -> 14 | G185: 5 | H185: 35 | I185: =IF(H185<>"",H185-G185,"") -> 30 | J185: Paid | K185: 46087 | L185: Renewed | M185: Private | N185: WeChat
A186: amrahhanane8@gmail.com | B186: chatgpt | C186: 1 Month | D186: 46091 | E186: =IF(C186<>"",D186+VLOOKUP(C186,$T$2:$U$6,2,FALSE),"") -> 46121 | F186: =IF(E186<>"",E186-TODAY(),"") -> 14 | G186: 5 | H186: 35 | I186: =IF(H186<>"",H186-G186,"") -> 30 | J186: Paid | K186: 46087 | L186: Renewed | M186: Private | N186: WeChat
A187: hossamgpts@gmail.com | B187: chatgpt | C187: 1 Month | D187: 46091 | E187: =IF(C187<>"",D187+VLOOKUP(C187,$T$2:$U$6,2,FALSE),"") -> 46121 | F187: =IF(E187<>"",E187-TODAY(),"") -> 14 | G187: 5 | H187: 35 | I187: =IF(H187<>"",H187-G187,"") -> 30 | J187: Paid | K187: 46087 | L187: Renewed | M187: Private | N187: WeChat
A188: sohzelbaalia@gmail.com | B188: chatgpt | C188: 1 Month | D188: 46091 | E188: =IF(C188<>"",D188+VLOOKUP(C188,$T$2:$U$6,2,FALSE),"") -> 46121 | F188: =IF(E188<>"",E188-TODAY(),"") -> 14 | G188: 5 | H188: 35 | I188: =IF(H188<>"",H188-G188,"") -> 30 | J188: CANCELED | K188: 46087 | L188: Renewed | M188: Private | N188: WeChat
A189: Yousofalkhateeb05@gmailcom | B189: chatgpt | C189: 1 Month | D189: 46091 | E189: =IF(C189<>"",D189+VLOOKUP(C189,$T$2:$U$6,2,FALSE),"") -> 46121 | F189: =IF(E189<>"",E189-TODAY(),"") -> 14 | G189: 5 | H189: 35 | I189: =IF(H189<>"",H189-G189,"") -> 30 | J189: Paid | K189: 46087 | L189: Renewed | M189: Private | N189: WeChat
A190: sevinchaysha@gmail.com | B190: chatgpt | C190: 1 Month | D190: 46091 | E190: =IF(C190<>"",D190+VLOOKUP(C190,$T$2:$U$6,2,FALSE),"") -> 46121 | F190: =IF(E190<>"",E190-TODAY(),"") -> 14 | G190: 5 | H190: 35 | I190: =IF(H190<>"",H190-G190,"") -> 30 | J190: Paid | K190: 46087 | L190: Renewed | M190: Private | N190: WeChat
A191: jackchina4286@gmail.com | B191: chatgpt | C191: 1 Month | D191: 46091 | E191: =IF(C191<>"",D191+VLOOKUP(C191,$T$2:$U$6,2,FALSE),"") -> 46121 | F191: =IF(E191<>"",E191-TODAY(),"") -> 14 | G191: 5 | H191: 35 | I191: =IF(H191<>"",H191-G191,"") -> 30 | J191: Paid | K191: 46087 | L191: Renewed | M191: Private | N191: WeChat
A192: Jackchhabria@gmail.com | B192: chatgpt | C192: 1 Month | D192: 46091 | E192: =IF(C192<>"",D192+VLOOKUP(C192,$T$2:$U$6,2,FALSE),"") -> 46121 | F192: =IF(E192<>"",E192-TODAY(),"") -> 14 | G192: 5 | H192: 35 | I192: =IF(H192<>"",H192-G192,"") -> 30 | J192: Paid | K192: 46087 | L192: Renewed | M192: Private | N192: WeChat
...

Sheet Dashboard
A1: TOTAL REVENUE | B1: =SUM('Client Subscriptions'!H:H) -> 14000
A2: TOTAL PROFIT | B2: =SUM('Client Subscriptions'!I:I) -> 11623
A3: ACTIVE SUBSCRIPTIONS | B3: =COUNTIF('Client Subscriptions'!F:F,">0") -> 283
A4: EXPIRING ≤4 DAYS | B4: =COUNTIFS('Client Subscriptions'!F:F,"<=4",'Client Subscriptions'!F:F,">0") -> 29
A5: EXPIRED | B5: =COUNTIF('Client Subscriptions'!F:F,"<=0") -> 18
A6: PENDING PAYMENTS | B6: =COUNTIF('Client Subscriptions'!J:J,"Pending") -> 13

Sheet Product Analytics
A1: Product | B1: Total Sales | C1: Total Profit
A2: Netflix | B2: =COUNTIF('Client Subscriptions'!B:B,A2) -> 6 | C2: =SUMIF('Client Subscriptions'!B:B,A2,'Client Subscriptions'!I:I) -> 101
A3: VPN | B3: =COUNTIF('Client Subscriptions'!B:B,A3) -> 16 | C3: =SUMIF('Client Subscriptions'!B:B,A3,'Client Subscriptions'!I:I) -> 577
A4: ChatGPT | B4: =COUNTIF('Client Subscriptions'!B:B,A4) -> 251 | C4: =SUMIF('Client Subscriptions'!B:B,A4,'Client Subscriptions'!I:I) -> 8965
A5: IPTV | B5: =COUNTIF('Client Subscriptions'!B:B,A5) -> 1 | C5: =SUMIF('Client Subscriptions'!B:B,A5,'Client Subscriptions'!I:I) -> 130
A6: Spotify | B6: =COUNTIF('Client Subscriptions'!B:B,A6) -> 5 | C6: =SUMIF('Client Subscriptions'!B:B,A6,'Client Subscriptions'!I:I) -> 160
A7: Canva | B7: =COUNTIF('Client Subscriptions'!B:B,A7) -> 3 | C7: =SUMIF('Client Subscriptions'!B:B,A7,'Client Subscriptions'!I:I) -> 165
A8: Apple One | B8: =COUNTIF('Client Subscriptions'!B:B,A8) -> 0 | C8: =SUMIF('Client Subscriptions'!B:B,A8,'Client Subscriptions'!I:I) -> 0
A9: perplexity ai | B9: 1 | C9: 40

Sheet Monthly Revenue
A1: Month | B1: Revenue
A2: Jan | B2: =SUMIFS('Client Subscriptions'!H:H, 'Client Subscriptions'!K:K,">="&DATE(YEAR(TODAY()),1,1), 'Client Subscriptions'!K:K,"<"&EOMONTH(DATE(YEAR(TODAY()),1,1),0)+1) -> 0
A3: Feb | B3: =SUMIFS('Client Subscriptions'!H:H, 'Client Subscriptions'!K:K,">="&DATE(YEAR(TODAY()),2,1), 'Client Subscriptions'!K:K,"<"&EOMONTH(DATE(YEAR(TODAY()),2,1),0)+1) -> 0
A4: Mar | B4: =SUMIFS('Client Subscriptions'!H:H, 'Client Subscriptions'!K:K,">="&DATE(YEAR(TODAY()),3,1), 'Client Subscriptions'!K:K,"<"&EOMONTH(DATE(YEAR(TODAY()),3,1),0)+1) -> 13940
A5: Apr | B5: =SUMIFS('Client Subscriptions'!H:H, 'Client Subscriptions'!K:K,">="&DATE(YEAR(TODAY()),4,1), 'Client Subscriptions'!K:K,"<"&EOMONTH(DATE(YEAR(TODAY()),4,1),0)+1) -> 0
A6: May | B6: =SUMIFS('Client Subscriptions'!H:H, 'Client Subscriptions'!K:K,">="&DATE(YEAR(TODAY()),5,1), 'Client Subscriptions'!K:K,"<"&EOMONTH(DATE(YEAR(TODAY()),5,1),0)+1) -> 0
A7: Jun | B7: =SUMIFS('Client Subscriptions'!H:H, 'Client Subscriptions'!K:K,">="&DATE(YEAR(TODAY()),6,1), 'Client Subscriptions'!K:K,"<"&EOMONTH(DATE(YEAR(TODAY()),6,1),0)+1) -> 0
A8: Jul | B8: =SUMIFS('Client Subscriptions'!H:H, 'Client Subscriptions'!K:K,">="&DATE(YEAR(TODAY()),7,1), 'Client Subscriptions'!K:K,"<"&EOMONTH(DATE(YEAR(TODAY()),7,1),0)+1) -> 0
A9: Aug | B9: =SUMIFS('Client Subscriptions'!H:H, 'Client Subscriptions'!K:K,">="&DATE(YEAR(TODAY()),8,1), 'Client Subscriptions'!K:K,"<"&EOMONTH(DATE(YEAR(TODAY()),8,1),0)+1) -> 0
A10: Sep | B10: =SUMIFS('Client Subscriptions'!H:H, 'Client Subscriptions'!K:K,">="&DATE(YEAR(TODAY()),9,1), 'Client Subscriptions'!K:K,"<"&EOMONTH(DATE(YEAR(TODAY()),9,1),0)+1) -> 0
A11: Oct | B11: =SUMIFS('Client Subscriptions'!H:H, 'Client Subscriptions'!K:K,">="&DATE(YEAR(TODAY()),10,1), 'Client Subscriptions'!K:K,"<"&EOMONTH(DATE(YEAR(TODAY()),10,1),0)+1) -> 0
A12: Nov | B12: =SUMIFS('Client Subscriptions'!H:H, 'Client Subscriptions'!K:K,">="&DATE(YEAR(TODAY()),11,1), 'Client Subscriptions'!K:K,"<"&EOMONTH(DATE(YEAR(TODAY()),11,1),0)+1) -> 0
A13: Dec | B13: =SUMIFS('Client Subscriptions'!H:H, 'Client Subscriptions'!K:K,">="&DATE(YEAR(TODAY()),12,1), 'Client Subscriptions'!K:K,"<"&EOMONTH(DATE(YEAR(TODAY()),12,1),0)+1) -> 0
